tests/__init__.py
tests/test_s3.py
upload_manager/__init__.py
upload_manager/admin.py
upload_manager/apps.py
upload_manager/file_operator.py
upload_manager/models.py
upload_manager/s3.py
upload_manager/service.py
upload_manager/urls.py
upload_manager/utils.py
upload_manager/views.py
upload_manager/migrations/0001_initial.py
upload_manager/migrations/__init__.py
upload_manager-1.1.1.dist-info/LICENSE.md
upload_manager-1.1.1.dist-info/METADATA
upload_manager-1.1.1.dist-info/WHEEL
upload_manager-1.1.1.dist-info/top_level.txt
upload_manager-1.1.1.dist-info/RECORD
