Metadata-Version: 2.1
Name: upload-manager
Version: 1.1.1
Summary: Upload manager
Home-page: https://github.com/Bigbasket/bbuploadmanager
Author: bb-tech
Author-email: asodiyadharmesh@gmail.com
Classifier: Programming Language :: Python :: 3
Classifier: Operating System :: OS Independent
Classifier: License :: OSI Approved :: MIT License
Classifier: Framework :: Django :: 2.1
Classifier: Topic :: Internet :: WWW/HTTP
Classifier: Topic :: Internet :: WWW/HTTP :: Dynamic Content
Requires-Python: >=3.6
License-File: LICENSE.md
Requires-Dist: boto3 ==1.10.38
Requires-Dist: chardet ==4.0.0
Requires-Dist: django ==2.1.4
Requires-Dist: python-environ ==0.4.54
